[
  {
    "nombre": "Arturo Salazar",
    "cedula": "",
    "edad": 13,
    "sexo": "",
    "ubicacion": "Hospital Pérez Carreño",
    "origen": "Caraballeda",
    "estado": "Hospitalizado",
    "verificado": false,
    "observacion": ""
  },
  {
    "nombre": "Eduan Orama",
    "cedula": "",
    "edad": null,
    "sexo": "",
    "ubicacion": "Hospital Pérez Carreño",
    "origen": "Tanaguare",
    "estado": "Hospitalizado",
    "verificado": false,
    "observacion": ""
  },
  {
    "nombre": "Xiomara Malave",
    "cedula": "",
    "edad": null,
    "sexo": "",
    "ubicacion": "Hospital Pérez Carreño",
    "origen": "Caraballeda",
    "estado": "Hospitalizado",
    "verificado": false,
    "observacion": ""
  },
  {
    "nombre": "Yesika Palmillaa",
    "cedula": "17960912",
    "edad": null,
    "sexo": "",
    "ubicacion": "Hospital Pérez Carreño",
    "origen": "Corales",
    "estado": "Hospitalizado",
    "verificado": false,
    "observacion": "Revisar nombre/origen"
  },
  {
    "nombre": "Diego Dias",
    "cedula": "",
    "edad": null,
    "sexo": "",
    "ubicacion": "Hospital Pérez Carreño",
    "origen": "",
    "estado": "Hospitalizado",
    "verificado": false,
    "observacion": ""
  },
  {
    "nombre": "Jemmy Ramirez",
    "cedula": "12171464",
    "edad": null,
    "sexo": "",
    "ubicacion": "Hospital Pérez Carreño",
    "origen": "",
    "estado": "Hospitalizado",
    "verificado": false,
    "observacion": ""
  },
  {
    "nombre": "Maria Ugas",
    "cedula": "11966827",
    "edad": null,
    "sexo": "",
    "ubicacion": "Hospital Pérez Carreño",
    "origen": "",
    "estado": "Hospitalizado",
    "verificado": false,
    "observacion": ""
  },
  {
    "nombre": "Junior Camacar",
    "cedula": "",
    "edad": 26,
    "sexo": "",
    "ubicacion": "Hospital Pérez Carreño",
    "origen": "",
    "estado": "Hospitalizado",
    "verificado": false,
    "observacion": ""
  },
  {
    "nombre": "Dario Ramirez",
    "cedula": "30824977",
    "edad": null,
    "sexo": "",
    "ubicacion": "Hospital Pérez Carreño",
    "origen": "",
    "estado": "Hospitalizado",
    "verificado": false,
    "observacion": ""
  },
  {
    "nombre": "Yuleivis Sandoval",
    "cedula": "",
    "edad": 74,
    "sexo": "",
    "ubicacion": "Hospital Pérez Carreño",
    "origen": "Maiquetia",
    "estado": "Hospitalizado",
    "verificado": false,
    "observacion": ""
  },
  {
    "nombre": "Rosis Gonzalez",
    "cedula": "",
    "edad": 41,
    "sexo": "",
    "ubicacion": "Hospital Pérez Carreño",
    "origen": "Caribe",
    "estado": "Hospitalizado",
    "verificado": false,
    "observacion": ""
  },
  {
    "nombre": "Alkelis Moron",
    "cedula": "",
    "edad": 50,
    "sexo": "",
    "ubicacion": "Hospital Pérez Carreño",
    "origen": "Caribe",
    "estado": "Hospitalizado",
    "verificado": false,
    "observacion": ""
  },
  {
    "nombre": "Antonio Herrera",
    "cedula": "",
    "edad": 83,
    "sexo": "",
    "ubicacion": "Hospital Pérez Carreño",
    "origen": "Macuto",
    "estado": "Hospitalizado",
    "verificado": false,
    "observacion": ""
  },
  {
    "nombre": "Kembelis Unsueto",
    "cedula": "",
    "edad": 38,
    "sexo": "",
    "ubicacion": "Hospital Pérez Carreño",
    "origen": "Corales",
    "estado": "Hospitalizado",
    "verificado": false,
    "observacion": ""
  },
  {
    "nombre": "Yoham Nillafand",
    "cedula": "",
    "edad": 36,
    "sexo": "",
    "ubicacion": "Hospital Pérez Carreño",
    "origen": "Macuto",
    "estado": "Hospitalizado",
    "verificado": false,
    "observacion": "Revisar nombre/origen"
  },
  {
    "nombre": "Ihoalvi Rosales",
    "cedula": "",
    "edad": 32,
    "sexo": "",
    "ubicacion": "Hospital Pérez Carreño",
    "origen": "Macuto",
    "estado": "Hospitalizado",
    "verificado": false,
    "observacion": "Revisar nombre/origen"
  },
  {
    "nombre": "Nestor Jose Nora",
    "cedula": "",
    "edad": 65,
    "sexo": "",
    "ubicacion": "Hospital Pérez Carreño",
    "origen": "Macuto",
    "estado": "Hospitalizado",
    "verificado": false,
    "observacion": ""
  },
  {
    "nombre": "Maira Viedra",
    "cedula": "",
    "edad": 64,
    "sexo": "",
    "ubicacion": "Hospital Pérez Carreño",
    "origen": "Corales",
    "estado": "Hospitalizado",
    "verificado": false,
    "observacion": ""
  },
  {
    "nombre": "Antonio Venditte",
    "cedula": "",
    "edad": 21,
    "sexo": "",
    "ubicacion": "Hospital Pérez Carreño",
    "origen": "Caraballeda",
    "estado": "Hospitalizado",
    "verificado": false,
    "observacion": "Revisar nombre/origen"
  },
  {
    "nombre": "Erik Salazar",
    "cedula": "",
    "edad": 45,
    "sexo": "",
    "ubicacion": "Hospital Pérez Carreño",
    "origen": "Caribe",
    "estado": "Hospitalizado",
    "verificado": false,
    "observacion": ""
  },
  {
    "nombre": "Horrada Ozcata",
    "cedula": "",
    "edad": 61,
    "sexo": "",
    "ubicacion": "Hospital Pérez Carreño",
    "origen": "Corales",
    "estado": "Hospitalizado",
    "verificado": false,
    "observacion": "Revisar nombre/origen"
  },
  {
    "nombre": "Tivisay Diaz",
    "cedula": "",
    "edad": 60,
    "sexo": "",
    "ubicacion": "Hospital Pérez Carreño",
    "origen": "Caribe",
    "estado": "Hospitalizado",
    "verificado": false,
    "observacion": ""
  },
  {
    "nombre": "Evelin Guerra",
    "cedula": "",
    "edad": 39,
    "sexo": "",
    "ubicacion": "Hospital Pérez Carreño",
    "origen": "Negra",
    "estado": "Hospitalizado",
    "verificado": false,
    "observacion": ""
  },
  {
    "nombre": "Lilibeth Gutierrez",
    "cedula": "",
    "edad": 43,
    "sexo": "",
    "ubicacion": "Hospital Pérez Carreño",
    "origen": "Caribe",
    "estado": "Hospitalizado",
    "verificado": false,
    "observacion": ""
  },
  {
    "nombre": "Argenis Landaeta",
    "cedula": "",
    "edad": 21,
    "sexo": "",
    "ubicacion": "Hospital Pérez Carreño",
    "origen": "Caribe",
    "estado": "Hospitalizado",
    "verificado": false,
    "observacion": ""
  },
  {
    "nombre": "Naike Sambrano",
    "cedula": "",
    "edad": 41,
    "sexo": "",
    "ubicacion": "Hospital Pérez Carreño",
    "origen": "",
    "estado": "Hospitalizado",
    "verificado": false,
    "observacion": ""
  },
  {
    "nombre": "Yonay Arias",
    "cedula": "",
    "edad": 52,
    "sexo": "",
    "ubicacion": "Hospital Pérez Carreño",
    "origen": "Costa Sos",
    "estado": "Hospitalizado",
    "verificado": false,
    "observacion": ""
  },
  {
    "nombre": "Vanesa Gonzalez",
    "cedula": "",
    "edad": 29,
    "sexo": "",
    "ubicacion": "Hospital Pérez Carreño",
    "origen": "Aeropuerto",
    "estado": "Hospitalizado",
    "verificado": false,
    "observacion": ""
  },
  {
    "nombre": "Duglas Merra",
    "cedula": "",
    "edad": 47,
    "sexo": "",
    "ubicacion": "Hospital Pérez Carreño",
    "origen": "Caribe",
    "estado": "Hospitalizado",
    "verificado": false,
    "observacion": "Revisar nombre/edad"
  },
  {
    "nombre": "Carlina Hernand",
    "cedula": "",
    "edad": 41,
    "sexo": "",
    "ubicacion": "Hospital Pérez Carreño",
    "origen": "Traslado",
    "estado": "Hospitalizado",
    "verificado": false,
    "observacion": "Revisar nombre/edad"
  },
  {
    "nombre": "Jose Sosa",
    "cedula": "",
    "edad": 40,
    "sexo": "",
    "ubicacion": "Hospital Pérez Carreño",
    "origen": "Caraballeda",
    "estado": "Hospitalizado",
    "verificado": false,
    "observacion": ""
  },
  {
    "nombre": "Luis Rodrigue",
    "cedula": "",
    "edad": 31,
    "sexo": "",
    "ubicacion": "Hospital Pérez Carreño",
    "origen": "Caraballeda",
    "estado": "Hospitalizado",
    "verificado": false,
    "observacion": ""
  },
  {
    "nombre": "Gisela Henrique",
    "cedula": "",
    "edad": 48,
    "sexo": "",
    "ubicacion": "Hospital Pérez Carreño",
    "origen": "Tanaguare",
    "estado": "Hospitalizado",
    "verificado": false,
    "observacion": ""
  },
  {
    "nombre": "Iose Villegas",
    "cedula": "",
    "edad": 22,
    "sexo": "",
    "ubicacion": "Hospital Pérez Carreño",
    "origen": "Caribe",
    "estado": "Hospitalizado",
    "verificado": false,
    "observacion": ""
  },
  {
    "nombre": "Iosue Alvarez",
    "cedula": "",
    "edad": 42,
    "sexo": "",
    "ubicacion": "Hospital Pérez Carreño",
    "origen": "Caribe",
    "estado": "Hospitalizado",
    "verificado": false,
    "observacion": ""
  },
  {
    "nombre": "Yasilis Carzadilla",
    "cedula": "",
    "edad": "50-30",
    "sexo": "",
    "ubicacion": "Hospital Pérez Carreño",
    "origen": "Caribe",
    "estado": "Hospitalizado",
    "verificado": false,
    "observacion": "Revisar nombre/edad"
  },
  {
    "nombre": "Maira Hernand",
    "cedula": "",
    "edad": 70,
    "sexo": "",
    "ubicacion": "Hospital Pérez Carreño",
    "origen": "Caribe",
    "estado": "Hospitalizado",
    "verificado": false,
    "observacion": ""
  },
  {
    "nombre": "Yonatan Romero",
    "cedula": "",
    "edad": 95,
    "sexo": "",
    "ubicacion": "Hospital Pérez Carreño",
    "origen": "Caribe",
    "estado": "Hospitalizado",
    "verificado": false,
    "observacion": ""
  },
  {
    "nombre": "Dani Sosa",
    "cedula": "",
    "edad": 54,
    "sexo": "",
    "ubicacion": "Hospital Pérez Carreño",
    "origen": "Caribe",
    "estado": "Hospitalizado",
    "verificado": false,
    "observacion": ""
  },
  {
    "nombre": "Genesis Silva",
    "cedula": "",
    "edad": 30,
    "sexo": "",
    "ubicacion": "Hospital Pérez Carreño",
    "origen": "Corales",
    "estado": "Hospitalizado",
    "verificado": false,
    "observacion": ""
  },
  {
    "nombre": "Olga Escobar",
    "cedula": "",
    "edad": null,
    "sexo": "",
    "ubicacion": "Hospital Pérez Carreño",
    "origen": "Corales",
    "estado": "Hospitalizado",
    "verificado": false,
    "observacion": ""
  },
  {
    "nombre": "Cesar Pacheco",
    "cedula": "26327366",
    "edad": null,
    "sexo": "",
    "ubicacion": "Hospital Pérez Carreño",
    "origen": "",
    "estado": "Hospitalizado",
    "verificado": false,
    "observacion": ""
  },
  {
    "nombre": "Ana Diaz",
    "cedula": "10576803",
    "edad": null,
    "sexo": "",
    "ubicacion": "Hospital Pérez Carreño",
    "origen": "",
    "estado": "Hospitalizado",
    "verificado": false,
    "observacion": ""
  },
  {
    "nombre": "Adriana Vastidas",
    "cedula": "17856045",
    "edad": null,
    "sexo": "",
    "ubicacion": "Hospital Pérez Carreño",
    "origen": "",
    "estado": "Hospitalizado",
    "verificado": false,
    "observacion": ""
  },
  {
    "nombre": "Petra Sucre",
    "cedula": "20003134",
    "edad": null,
    "sexo": "",
    "ubicacion": "Hospital Pérez Carreño",
    "origen": "",
    "estado": "Hospitalizado",
    "verificado": false,
    "observacion": ""
  },
  {
    "nombre": "Wiliam Alvarez",
    "cedula": "16125101",
    "edad": null,
    "sexo": "",
    "ubicacion": "Hospital Pérez Carreño",
    "origen": "",
    "estado": "Hospitalizado",
    "verificado": false,
    "observacion": ""
  },
  {
    "nombre": "Alexandra Cardenas",
    "cedula": "28143770",
    "edad": null,
    "sexo": "",
    "ubicacion": "Hospital Pérez Carreño",
    "origen": "",
    "estado": "Hospitalizado",
    "verificado": false,
    "observacion": ""
  },
  {
    "nombre": "Francis Medina",
    "cedula": "285659",
    "edad": null,
    "sexo": "",
    "ubicacion": "Hospital Pérez Carreño",
    "origen": "",
    "estado": "Hospitalizado",
    "verificado": false,
    "observacion": "Revisar nombre/edad"
  },
  {
    "nombre": "Cruz Hernand",
    "cedula": "4636722",
    "edad": null,
    "sexo": "",
    "ubicacion": "Hospital Pérez Carreño",
    "origen": "",
    "estado": "Hospitalizado",
    "verificado": false,
    "observacion": "Revisar nombre/edad"
  },
  {
    "nombre": "Fran Rondon",
    "cedula": "19659867",
    "edad": null,
    "sexo": "",
    "ubicacion": "Hospital Pérez Carreño",
    "origen": "",
    "estado": "Hospitalizado",
    "verificado": false,
    "observacion": ""
  },
  {
    "nombre": "Leonardo Becerra",
    "cedula": "34800366",
    "edad": null,
    "sexo": "",
    "ubicacion": "Hospital Pérez Carreño",
    "origen": "",
    "estado": "Hospitalizado",
    "verificado": false,
    "observacion": ""
  },
  {
    "nombre": "Cenaida Paredez",
    "cedula": "6405488",
    "edad": null,
    "sexo": "",
    "ubicacion": "Hospital Pérez Carreño",
    "origen": "",
    "estado": "Hospitalizado",
    "verificado": false,
    "observacion": ""
  },
  {
    "nombre": "Oriana Ramirez",
    "cedula": "27006264",
    "edad": null,
    "sexo": "",
    "ubicacion": "Hospital Pérez Carreño",
    "origen": "",
    "estado": "Hospitalizado",
    "verificado": false,
    "observacion": ""
  },
  {
    "nombre": "Judid Paredes",
    "cedula": "3883421",
    "edad": null,
    "sexo": "",
    "ubicacion": "Hospital Pérez Carreño",
    "origen": "",
    "estado": "Hospitalizado",
    "verificado": false,
    "observacion": "Revisar nombre"
  },
  {
    "nombre": "Yadira Cordero",
    "cedula": "12763837",
    "edad": null,
    "sexo": "",
    "ubicacion": "Hospital Pérez Carreño",
    "origen": "",
    "estado": "Hospitalizado",
    "verificado": false,
    "observacion": ""
  },
  {
    "nombre": "Dayanara Rondon",
    "cedula": "",
    "edad": 18,
    "sexo": "",
    "ubicacion": "Hospital Pérez Carreño",
    "origen": "",
    "estado": "Hospitalizado",
    "verificado": false,
    "observacion": ""
  },
  {
    "nombre": "Crisdelis Quintero",
    "cedula": "32865296",
    "edad": null,
    "sexo": "",
    "ubicacion": "Hospital Pérez Carreño",
    "origen": "",
    "estado": "Hospitalizado",
    "verificado": false,
    "observacion": ""
  },
  {
    "nombre": "Erik Godoy",
    "cedula": "18749225",
    "edad": null,
    "sexo": "",
    "ubicacion": "Hospital Pérez Carreño",
    "origen": "",
    "estado": "Hospitalizado",
    "verificado": false,
    "observacion": ""
  },
  {
    "nombre": "Nayibi Molina",
    "cedula": "29768360",
    "edad": null,
    "sexo": "",
    "ubicacion": "Hospital Pérez Carreño",
    "origen": "",
    "estado": "Hospitalizado",
    "verificado": false,
    "observacion": ""
  },
  {
    "nombre": "Maria Zamora",
    "cedula": "27044236",
    "edad": null,
    "sexo": "",
    "ubicacion": "Hospital Pérez Carreño",
    "origen": "",
    "estado": "Hospitalizado",
    "verificado": false,
    "observacion": ""
  },
  {
    "nombre": "Petra Sucre",
    "cedula": "2945823",
    "edad": null,
    "sexo": "",
    "ubicacion": "Hospital Pérez Carreño",
    "origen": "",
    "estado": "Hospitalizado",
    "verificado": false,
    "observacion": ""
  },
  {
    "nombre": "Wiliam Alvarez",
    "cedula": "16125101",
    "edad": null,
    "sexo": "",
    "ubicacion": "Hospital Pérez Carreño",
    "origen": "",
    "estado": "Hospitalizado",
    "verificado": false,
    "observacion": ""
  },
  {
    "nombre": "Juan Salazar",
    "cedula": "27044236",
    "edad": null,
    "sexo": "",
    "ubicacion": "Hospital Pérez Carreño",
    "origen": "",
    "estado": "Hospitalizado",
    "verificado": false,
    "observacion": ""
  },
  {
    "nombre": "Veronica Bastardo",
    "cedula": "30170626",
    "edad": null,
    "sexo": "",
    "ubicacion": "Hospital Pérez Carreño",
    "origen": "",
    "estado": "Hospitalizado",
    "verificado": false,
    "observacion": ""
  },
  {
    "nombre": "Isabel Gonzalez",
    "cedula": "29701695",
    "edad": null,
    "sexo": "",
    "ubicacion": "Hospital Pérez Carreño",
    "origen": "",
    "estado": "Hospitalizado",
    "verificado": false,
    "observacion": ""
  },
  {
    "nombre": "Elianni Hidalgo",
    "cedula": "32976229",
    "edad": null,
    "sexo": "",
    "ubicacion": "Hospital Pérez Carreño",
    "origen": "",
    "estado": "Hospitalizado",
    "verificado": false,
    "observacion": ""
  },
  {
    "nombre": "Franleyon Lopez",
    "cedula": "",
    "edad": null,
    "sexo": "",
    "ubicacion": "Hospital Pérez Carreño",
    "origen": "",
    "estado": "Hospitalizado",
    "verificado": false,
    "observacion": "Revisar nombre"
  },
  {
    "nombre": "Amilcar Stanilito",
    "cedula": "23241059",
    "edad": null,
    "sexo": "",
    "ubicacion": "Hospital Pérez Carreño",
    "origen": "",
    "estado": "Hospitalizado",
    "verificado": false,
    "observacion": "Revisar nombre"
  },
  {
    "nombre": "Yodalis Navas",
    "cedula": "30072743",
    "edad": null,
    "sexo": "",
    "ubicacion": "Hospital Pérez Carreño",
    "origen": "",
    "estado": "Hospitalizado",
    "verificado": false,
    "observacion": ""
  },
  {
    "nombre": "Gabriel Goncalve",
    "cedula": "82230906",
    "edad": null,
    "sexo": "",
    "ubicacion": "Hospital Pérez Carreño",
    "origen": "",
    "estado": "Hospitalizado",
    "verificado": false,
    "observacion": "Revisar nombre"
  },
  {
    "nombre": "Zoraida Martinez",
    "cedula": "6092167",
    "edad": null,
    "sexo": "",
    "ubicacion": "Hospital Pérez Carreño",
    "origen": "",
    "estado": "Hospitalizado",
    "verificado": false,
    "observacion": ""
  },
  {
    "nombre": "Rosa Marcano",
    "cedula": "4493435",
    "edad": null,
    "sexo": "",
    "ubicacion": "Hospital Pérez Carreño",
    "origen": "",
    "estado": "Hospitalizado",
    "verificado": false,
    "observacion": ""
  },
  {
    "nombre": "Adriana Sandoval",
    "cedula": "34518879",
    "edad": null,
    "sexo": "",
    "ubicacion": "Hospital Pérez Carreño",
    "origen": "",
    "estado": "Hospitalizado",
    "verificado": false,
    "observacion": ""
  },
  {
    "nombre": "Victoria Miranda",
    "cedula": "34054588",
    "edad": null,
    "sexo": "",
    "ubicacion": "Hospital Pérez Carreño",
    "origen": "",
    "estado": "Hospitalizado",
    "verificado": false,
    "observacion": ""
  },
  {
    "nombre": "Jose Gutierrez",
    "cedula": "28747519",
    "edad": null,
    "sexo": "",
    "ubicacion": "Hospital Pérez Carreño",
    "origen": "",
    "estado": "Hospitalizado",
    "verificado": false,
    "observacion": ""
  },
  {
    "nombre": "Eduar Orana",
    "cedula": "",
    "edad": null,
    "sexo": "",
    "ubicacion": "Hospital Pérez Carreño",
    "origen": "",
    "estado": "Hospitalizado",
    "verificado": false,
    "observacion": "Revisar nombre/origen"
  },
  {
    "nombre": "Mileibis Gonzalez",
    "cedula": "26468240",
    "edad": null,
    "sexo": "",
    "ubicacion": "Hospital Pérez Carreño",
    "origen": "",
    "estado": "Hospitalizado",
    "verificado": false,
    "observacion": ""
  },
  {
    "nombre": "Emira Guerra",
    "cedula": "26019884",
    "edad": null,
    "sexo": "",
    "ubicacion": "Hospital Pérez Carreño",
    "origen": "",
    "estado": "Hospitalizado",
    "verificado": false,
    "observacion": ""
  },
  {
    "nombre": "Keilimar Garcia",
    "cedula": "32543420",
    "edad": null,
    "sexo": "",
    "ubicacion": "Hospital Pérez Carreño",
    "origen": "",
    "estado": "Hospitalizado",
    "verificado": false,
    "observacion": ""
  },
  {
    "nombre": "Gabriel Brizuela",
    "cedula": "32781459",
    "edad": null,
    "sexo": "",
    "ubicacion": "Hospital Pérez Carreño",
    "origen": "",
    "estado": "Hospitalizado",
    "verificado": false,
    "observacion": ""
  },
  {
    "nombre": "Vivian Carrizo",
    "cedula": "33232603",
    "edad": null,
    "sexo": "",
    "ubicacion": "Hospital Pérez Carreño",
    "origen": "",
    "estado": "Hospitalizado",
    "verificado": false,
    "observacion": ""
  },
  {
    "nombre": "Diego Garcia",
    "cedula": "33423811",
    "edad": null,
    "sexo": "",
    "ubicacion": "Hospital Pérez Carreño",
    "origen": "",
    "estado": "Hospitalizado",
    "verificado": false,
    "observacion": ""
  },
  {
    "nombre": "Adrian Espinoza",
    "cedula": "",
    "edad": null,
    "sexo": "",
    "ubicacion": "Hospital Pérez Carreño",
    "origen": "Guaira",
    "estado": "Hospitalizado",
    "verificado": false,
    "observacion": ""
  },
  {
    "nombre": "Asly Janaise Carreño",
    "cedula": "",
    "edad": null,
    "sexo": "",
    "ubicacion": "Hospital Pérez Carreño",
    "origen": "La Guaira",
    "estado": "Hospitalizado",
    "verificado": false,
    "observacion": ""
  },
  {
    "nombre": "Luisa Gonzalez",
    "cedula": "",
    "edad": null,
    "sexo": "",
    "ubicacion": "Hospital Pérez Carreño",
    "origen": "Catia La",
    "estado": "Hospitalizado",
    "verificado": false,
    "observacion": ""
  },
  {
    "nombre": "Erick Dorante",
    "cedula": "",
    "edad": null,
    "sexo": "",
    "ubicacion": "Hospital Pérez Carreño",
    "origen": "Tanaguare",
    "estado": "Hospitalizado",
    "verificado": false,
    "observacion": ""
  },
  {
    "nombre": "Cristian Orteaga",
    "cedula": "",
    "edad": null,
    "sexo": "",
    "ubicacion": "Hospital Pérez Carreño",
    "origen": "Tanaguare",
    "estado": "Hospitalizado",
    "verificado": false,
    "observacion": "Revisar nombre/origen"
  },
  {
    "nombre": "Ashlys Carreño",
    "cedula": "",
    "edad": null,
    "sexo": "",
    "ubicacion": "Hospital Pérez Carreño",
    "origen": "Caribe",
    "estado": "Hospitalizado",
    "verificado": false,
    "observacion": ""
  },
  {
    "nombre": "Derek Josue Carreño",
    "cedula": "",
    "edad": null,
    "sexo": "",
    "ubicacion": "Hospital Pérez Carreño",
    "origen": "Caribe",
    "estado": "Hospitalizado",
    "verificado": false,
    "observacion": ""
  },
  {
    "nombre": "Iose Uzcategui",
    "cedula": "",
    "edad": null,
    "sexo": "",
    "ubicacion": "Hospital Pérez Carreño",
    "origen": "Corales",
    "estado": "Hospitalizado",
    "verificado": false,
    "observacion": ""
  },
  {
    "nombre": "Ilegible Romero",
    "cedula": "",
    "edad": null,
    "sexo": "",
    "ubicacion": "Hospital Pérez Carreño",
    "origen": "Carinbe",
    "estado": "Hospitalizado",
    "verificado": false,
    "observacion": "Revisar nombre/origen"
  },
  {
    "nombre": "Francisco Oropeza",
    "cedula": "",
    "edad": null,
    "sexo": "",
    "ubicacion": "Hospital Pérez Carreño",
    "origen": "La Guaira",
    "estado": "Hospitalizado",
    "verificado": false,
    "observacion": ""
  },
  {
    "nombre": "Iairo Da Silva",
    "cedula": "",
    "edad": null,
    "sexo": "",
    "ubicacion": "Hospital Pérez Carreño",
    "origen": "Guaira",
    "estado": "Hospitalizado",
    "verificado": false,
    "observacion": "Revisar nombre/origen"
  },
  {
    "nombre": "Andres Lorva",
    "cedula": "",
    "edad": null,
    "sexo": "",
    "ubicacion": "Hospital Pérez Carreño",
    "origen": "Caribe",
    "estado": "Hospitalizado",
    "verificado": false,
    "observacion": "Revisar nombre/origen"
  },
  {
    "nombre": "Noel La Rosa",
    "cedula": "",
    "edad": null,
    "sexo": "",
    "ubicacion": "Hospital Pérez Carreño",
    "origen": "Hotel",
    "estado": "Hospitalizado",
    "verificado": false,
    "observacion": ""
  },
  {
    "nombre": "Carlina Hernand",
    "cedula": "",
    "edad": null,
    "sexo": "",
    "ubicacion": "Hospital Pérez Carreño",
    "origen": "Caraballeda",
    "estado": "Hospitalizado",
    "verificado": false,
    "observacion": ""
  },
  {
    "nombre": "Anderson Mendoza",
    "cedula": "",
    "edad": null,
    "sexo": "",
    "ubicacion": "Hospital Pérez Carreño",
    "origen": "playa",
    "estado": "Hospitalizado",
    "verificado": false,
    "observacion": ""
  },
  {
    "nombre": "Yeangel Figueroa",
    "cedula": "",
    "edad": null,
    "sexo": "",
    "ubicacion": "Hospital Pérez Carreño",
    "origen": "Tanaguare",
    "estado": "Hospitalizado",
    "verificado": false,
    "observacion": ""
  },
  {
    "nombre": "Alfredo Quintero",
    "cedula": "",
    "edad": null,
    "sexo": "",
    "ubicacion": "Hospital Pérez Carreño",
    "origen": "Playa",
    "estado": "Hospitalizado",
    "verificado": false,
    "observacion": ""
  },
  {
    "nombre": "Eclwin Urbina",
    "cedula": "",
    "edad": null,
    "sexo": "",
    "ubicacion": "Hospital Pérez Carreño",
    "origen": "Caraballeda",
    "estado": "Hospitalizado",
    "verificado": false,
    "observacion": "Revisar nombre/origen"
  },
  {
    "nombre": "Isabela Revoredo",
    "cedula": "",
    "edad": null,
    "sexo": "",
    "ubicacion": "Hospital Pérez Carreño",
    "origen": "Caribe",
    "estado": "Hospitalizado",
    "verificado": false,
    "observacion": ""
  },
  {
    "nombre": "Carmelo Figuera",
    "cedula": "",
    "edad": null,
    "sexo": "",
    "ubicacion": "Hospital Pérez Carreño",
    "origen": "Caraballeda",
    "estado": "Hospitalizado",
    "verificado": false,
    "observacion": ""
  },
  {
    "nombre": "Luis Lopez",
    "cedula": "",
    "edad": null,
    "sexo": "",
    "ubicacion": "Hospital Pérez Carreño",
    "origen": "Caraballeda",
    "estado": "Hospitalizado",
    "verificado": false,
    "observacion": ""
  },
  {
    "nombre": "Morilda Figuera",
    "cedula": "",
    "edad": null,
    "sexo": "",
    "ubicacion": "Hospital Pérez Carreño",
    "origen": "Guaira",
    "estado": "Hospitalizado",
    "verificado": false,
    "observacion": ""
  },
  {
    "nombre": "Almando Medina",
    "cedula": "",
    "edad": null,
    "sexo": "",
    "ubicacion": "Hospital Pérez Carreño",
    "origen": "Playa",
    "estado": "Hospitalizado",
    "verificado": false,
    "observacion": ""
  },
  {
    "nombre": "Amgi Sanabria",
    "cedula": "",
    "edad": null,
    "sexo": "",
    "ubicacion": "Hospital Pérez Carreño",
    "origen": "Guaira",
    "estado": "Hospitalizado",
    "verificado": false,
    "observacion": "Revisar nombre"
  },
  {
    "nombre": "Damian Vargas",
    "cedula": "",
    "edad": null,
    "sexo": "",
    "ubicacion": "Hospital Pérez Carreño",
    "origen": "Catia Agua",
    "estado": "Hospitalizado",
    "verificado": false,
    "observacion": ""
  },
  {
    "nombre": "Yosbelly Rodrigue",
    "cedula": "",
    "edad": null,
    "sexo": "",
    "ubicacion": "Hospital Pérez Carreño",
    "origen": "Caribe",
    "estado": "Hospitalizado",
    "verificado": false,
    "observacion": "Revisar nombre"
  },
  {
    "nombre": "Yoneiver Rodrigue",
    "cedula": "",
    "edad": null,
    "sexo": "",
    "ubicacion": "Hospital Pérez Carreño",
    "origen": "Caribe",
    "estado": "Hospitalizado",
    "verificado": false,
    "observacion": "Revisar nombre"
  },
  {
    "nombre": "Iesus Gonzalez",
    "cedula": "",
    "edad": null,
    "sexo": "",
    "ubicacion": "Hospital Pérez Carreño",
    "origen": "Guaira",
    "estado": "Hospitalizado",
    "verificado": false,
    "observacion": "Revisar nombre"
  },
  {
    "nombre": "Valeska Toro",
    "cedula": "",
    "edad": null,
    "sexo": "",
    "ubicacion": "Hospital Pérez Carreño",
    "origen": "Tanaguare",
    "estado": "Hospitalizado",
    "verificado": false,
    "observacion": ""
  },
  {
    "nombre": "Maria Albarran",
    "cedula": "",
    "edad": null,
    "sexo": "",
    "ubicacion": "Hospital Pérez Carreño",
    "origen": "La Vega",
    "estado": "Hospitalizado",
    "verificado": false,
    "observacion": ""
  },
  {
    "nombre": "Jose Parra",
    "cedula": "",
    "edad": null,
    "sexo": "",
    "ubicacion": "Hospital Pérez Carreño",
    "origen": "",
    "estado": "Hospitalizado",
    "verificado": false,
    "observacion": ""
  },
  {
    "nombre": "Wiliam Jose Cordero",
    "cedula": "",
    "edad": null,
    "sexo": "",
    "ubicacion": "Hospital Pérez Carreño",
    "origen": "",
    "estado": "Hospitalizado",
    "verificado": false,
    "observacion": ""
  },
  {
    "nombre": "Anabella Morillo",
    "cedula": "",
    "edad": null,
    "sexo": "",
    "ubicacion": "Hospital Pérez Carreño",
    "origen": "",
    "estado": "Hospitalizado",
    "verificado": false,
    "observacion": ""
  },
  {
    "nombre": "Yanelis del Acosta",
    "cedula": "",
    "edad": null,
    "sexo": "",
    "ubicacion": "Hospital Pérez Carreño",
    "origen": "",
    "estado": "Hospitalizado",
    "verificado": false,
    "observacion": "Revisar nombre"
  },
  {
    "nombre": "Lian Polanco",
    "cedula": "",
    "edad": null,
    "sexo": "",
    "ubicacion": "Hospital Pérez Carreño",
    "origen": "Av. Baral",
    "estado": "Hospitalizado",
    "verificado": false,
    "observacion": ""
  },
  {
    "nombre": "Geenesis Yauripans",
    "cedula": "",
    "edad": null,
    "sexo": "",
    "ubicacion": "Hospital Pérez Carreño",
    "origen": "",
    "estado": "Hospitalizado",
    "verificado": false,
    "observacion": "Revisar nombre"
  },
  {
    "nombre": "Maria Loabel",
    "cedula": "",
    "edad": null,
    "sexo": "",
    "ubicacion": "Hospital Pérez Carreño",
    "origen": "",
    "estado": "Hospitalizado",
    "verificado": false,
    "observacion": "Revisar nombre"
  },
  {
    "nombre": "Lain Diske",
    "cedula": "",
    "edad": null,
    "sexo": "",
    "ubicacion": "Hospital Pérez Carreño",
    "origen": "",
    "estado": "Hospitalizado",
    "verificado": false,
    "observacion": "Revisar nombre"
  },
  {
    "nombre": "Johan Salazar",
    "cedula": "",
    "edad": null,
    "sexo": "",
    "ubicacion": "Hospital Pérez Carreño",
    "origen": "",
    "estado": "Hospitalizado",
    "verificado": false,
    "observacion": ""
  },
  {
    "nombre": "Isabel Gonzalez",
    "cedula": "",
    "edad": null,
    "sexo": "",
    "ubicacion": "Hospital Pérez Carreño",
    "origen": "",
    "estado": "Hospitalizado",
    "verificado": false,
    "observacion": ""
  },
  {
    "nombre": "Giannis Dvon",
    "cedula": "",
    "edad": null,
    "sexo": "",
    "ubicacion": "Hospital Pérez Carreño",
    "origen": "",
    "estado": "Hospitalizado",
    "verificado": false,
    "observacion": "Revisar nombre"
  },
  {
    "nombre": "Yunior Loveiz",
    "cedula": "",
    "edad": null,
    "sexo": "",
    "ubicacion": "Hospital Pérez Carreño",
    "origen": "",
    "estado": "Hospitalizado",
    "verificado": false,
    "observacion": "Revisar nombre"
  },
  {
    "nombre": "Maria Iose Anaque",
    "cedula": "",
    "edad": null,
    "sexo": "",
    "ubicacion": "Hospital Pérez Carreño",
    "origen": "",
    "estado": "Hospitalizado",
    "verificado": false,
    "observacion": "Revisar nombre"
  },
  {
    "nombre": "Barbara Ramirez",
    "cedula": "",
    "edad": null,
    "sexo": "",
    "ubicacion": "Hospital Pérez Carreño",
    "origen": "",
    "estado": "Hospitalizado",
    "verificado": false,
    "observacion": ""
  },
  {
    "nombre": "Brayan Brito",
    "cedula": "",
    "edad": null,
    "sexo": "",
    "ubicacion": "Hospital Pérez Carreño",
    "origen": "",
    "estado": "Hospitalizado",
    "verificado": false,
    "observacion": ""
  },
  {
    "nombre": "Miz Acevedo",
    "cedula": "",
    "edad": null,
    "sexo": "",
    "ubicacion": "Hospital Pérez Carreño",
    "origen": "",
    "estado": "Hospitalizado",
    "verificado": false,
    "observacion": "Revisar nombre"
  },
  {
    "nombre": "Antonella Brito",
    "cedula": "",
    "edad": 11,
    "sexo": "",
    "ubicacion": "Hospital Pérez Carreño",
    "origen": "Catia La",
    "estado": "Hospitalizado",
    "verificado": false,
    "observacion": ""
  },
  {
    "nombre": "Jose Palma",
    "cedula": "",
    "edad": null,
    "sexo": "",
    "ubicacion": "Hospital Pérez Carreño",
    "origen": "",
    "estado": "Hospitalizado",
    "verificado": false,
    "observacion": ""
  },
  {
    "nombre": "Caren Anzarita",
    "cedula": "",
    "edad": null,
    "sexo": "",
    "ubicacion": "Hospital Pérez Carreño",
    "origen": "",
    "estado": "Hospitalizado",
    "verificado": false,
    "observacion": ""
  },
  {
    "nombre": "Yohadi Abel Colina",
    "cedula": "",
    "edad": null,
    "sexo": "",
    "ubicacion": "Hospital Pérez Carreño",
    "origen": "",
    "estado": "Hospitalizado",
    "verificado": false,
    "observacion": ""
  },
  {
    "nombre": "Yerman Ilegible",
    "cedula": "",
    "edad": null,
    "sexo": "",
    "ubicacion": "Hospital Pérez Carreño",
    "origen": "",
    "estado": "Hospitalizado",
    "verificado": false,
    "observacion": "Revisar nombre"
  },
  {
    "nombre": "Brianyelys Draz",
    "cedula": "",
    "edad": null,
    "sexo": "",
    "ubicacion": "Hospital Pérez Carreño",
    "origen": "",
    "estado": "Hospitalizado",
    "verificado": false,
    "observacion": "Revisar nombre"
  },
  {
    "nombre": "Hanser Medina",
    "cedula": "",
    "edad": null,
    "sexo": "",
    "ubicacion": "Hospital Pérez Carreño",
    "origen": "",
    "estado": "Hospitalizado",
    "verificado": false,
    "observacion": ""
  },
  {
    "nombre": "Fabian Gonzalez",
    "cedula": "",
    "edad": null,
    "sexo": "",
    "ubicacion": "Hospital Pérez Carreño",
    "origen": "",
    "estado": "Hospitalizado",
    "verificado": false,
    "observacion": ""
  },
  {
    "nombre": "Marlyn Martinez",
    "cedula": "",
    "edad": null,
    "sexo": "",
    "ubicacion": "Hospital Pérez Carreño",
    "origen": "",
    "estado": "Hospitalizado",
    "verificado": false,
    "observacion": ""
  },
  {
    "nombre": "Cesar Diaz",
    "cedula": "",
    "edad": null,
    "sexo": "",
    "ubicacion": "Hospital Pérez Carreño",
    "origen": "",
    "estado": "Hospitalizado",
    "verificado": false,
    "observacion": ""
  },
  {
    "nombre": "Freddy Rodrigue",
    "cedula": "",
    "edad": null,
    "sexo": "",
    "ubicacion": "Hospital Pérez Carreño",
    "origen": "",
    "estado": "Hospitalizado",
    "verificado": false,
    "observacion": ""
  },
  {
    "nombre": "Ana Felicia Dias",
    "cedula": "",
    "edad": null,
    "sexo": "",
    "ubicacion": "Hospital Pérez Carreño",
    "origen": "",
    "estado": "Hospitalizado",
    "verificado": false,
    "observacion": ""
  },
  {
    "nombre": "Jose Medina",
    "cedula": "",
    "edad": 5,
    "sexo": "",
    "ubicacion": "Hospital Pérez Carreño",
    "origen": "Junquito",
    "estado": "Hospitalizado",
    "verificado": false,
    "observacion": ""
  },
  {
    "nombre": "Laiyum Parica",
    "cedula": "",
    "edad": 1,
    "sexo": "",
    "ubicacion": "Hospital Pérez Carreño",
    "origen": "Catia La",
    "estado": "Hospitalizado",
    "verificado": false,
    "observacion": "Revisar nombre"
  },
  {
    "nombre": "Mia Acevedo",
    "cedula": "",
    "edad": null,
    "sexo": "",
    "ubicacion": "Hospital Pérez Carreño",
    "origen": "Catia La",
    "estado": "Hospitalizado",
    "verificado": false,
    "observacion": ""
  },
  {
    "nombre": "Diego Orozco",
    "cedula": "",
    "edad": 8,
    "sexo": "",
    "ubicacion": "Hospital Pérez Carreño",
    "origen": "",
    "estado": "Hospitalizado",
    "verificado": false,
    "observacion": ""
  },
  {
    "nombre": "Aranza Vergara",
    "cedula": "",
    "edad": 1,
    "sexo": "",
    "ubicacion": "Hospital Pérez Carreño",
    "origen": "Tanaguare",
    "estado": "Hospitalizado",
    "verificado": false,
    "observacion": ""
  },
  {
    "nombre": "Jesus Rodriguez",
    "cedula": "",
    "edad": 9,
    "sexo": "",
    "ubicacion": "Hospital Pérez Carreño",
    "origen": "Guaira",
    "estado": "Hospitalizado",
    "verificado": false,
    "observacion": ""
  },
  {
    "nombre": "Emili Ramos",
    "cedula": "",
    "edad": 10,
    "sexo": "",
    "ubicacion": "Hospital Pérez Carreño",
    "origen": "",
    "estado": "Hospitalizado",
    "verificado": false,
    "observacion": ""
  },
  {
    "nombre": "Yordana Flores",
    "cedula": "",
    "edad": 10,
    "sexo": "",
    "ubicacion": "Hospital Pérez Carreño",
    "origen": "Caraballeda",
    "estado": "Hospitalizado",
    "verificado": false,
    "observacion": ""
  },
  {
    "nombre": "Aron Isaac Villalobos",
    "cedula": "",
    "edad": null,
    "sexo": "",
    "ubicacion": "Hospital Pérez Carreño",
    "origen": "Tanaguare",
    "estado": "Hospitalizado",
    "verificado": false,
    "observacion": ""
  },
  {
    "nombre": "Yenni Marcano",
    "cedula": "18384289",
    "edad": null,
    "sexo": "",
    "ubicacion": "Hospital Pérez Carreño",
    "origen": "",
    "estado": "Hospitalizado",
    "verificado": false,
    "observacion": ""
  },
  {
    "nombre": "Manuela De",
    "cedula": "296723",
    "edad": null,
    "sexo": "",
    "ubicacion": "Hospital Pérez Carreño",
    "origen": "",
    "estado": "Hospitalizado",
    "verificado": false,
    "observacion": "Revisar nombre"
  },
  {
    "nombre": "Gonzalo Leon",
    "cedula": "22916224",
    "edad": null,
    "sexo": "",
    "ubicacion": "Hospital Pérez Carreño",
    "origen": "",
    "estado": "Hospitalizado",
    "verificado": false,
    "observacion": ""
  },
  {
    "nombre": "Yonny Ortuño",
    "cedula": "5199652",
    "edad": null,
    "sexo": "",
    "ubicacion": "Hospital Pérez Carreño",
    "origen": "",
    "estado": "Hospitalizado",
    "verificado": false,
    "observacion": ""
  },
  {
    "nombre": "Ana Fernande",
    "cedula": "25699054",
    "edad": null,
    "sexo": "",
    "ubicacion": "Hospital Pérez Carreño",
    "origen": "",
    "estado": "Hospitalizado",
    "verificado": false,
    "observacion": "Revisar nombre"
  },
  {
    "nombre": "Alyandra Soja",
    "cedula": "6904629",
    "edad": null,
    "sexo": "",
    "ubicacion": "Hospital Pérez Carreño",
    "origen": "",
    "estado": "Hospitalizado",
    "verificado": false,
    "observacion": "Revisar nombre"
  },
  {
    "nombre": "Eliban Yegue",
    "cedula": "24038780",
    "edad": null,
    "sexo": "",
    "ubicacion": "Hospital Pérez Carreño",
    "origen": "",
    "estado": "Hospitalizado",
    "verificado": false,
    "observacion": "Revisar nombre"
  },
  {
    "nombre": "Marcela Bernal",
    "cedula": "6049995",
    "edad": null,
    "sexo": "",
    "ubicacion": "Hospital Pérez Carreño",
    "origen": "",
    "estado": "Hospitalizado",
    "verificado": false,
    "observacion": ""
  },
  {
    "nombre": "Valeria Azocar",
    "cedula": "28544619",
    "edad": null,
    "sexo": "",
    "ubicacion": "Hospital Pérez Carreño",
    "origen": "",
    "estado": "Hospitalizado",
    "verificado": false,
    "observacion": ""
  },
  {
    "nombre": "Lesvia Morales",
    "cedula": "5965096",
    "edad": null,
    "sexo": "",
    "ubicacion": "Hospital Pérez Carreño",
    "origen": "",
    "estado": "Hospitalizado",
    "verificado": false,
    "observacion": ""
  },
  {
    "nombre": "Merido Bueno",
    "cedula": "17158021",
    "edad": null,
    "sexo": "",
    "ubicacion": "Hospital Pérez Carreño",
    "origen": "",
    "estado": "Hospitalizado",
    "verificado": false,
    "observacion": ""
  },
  {
    "nombre": "Maria Montoya",
    "cedula": "",
    "edad": null,
    "sexo": "",
    "ubicacion": "Hospital Pérez Carreño",
    "origen": "",
    "estado": "Hospitalizado",
    "verificado": false,
    "observacion": ""
  },
  {
    "nombre": "Isabel Torres",
    "cedula": "4718019",
    "edad": null,
    "sexo": "",
    "ubicacion": "Hospital Pérez Carreño",
    "origen": "",
    "estado": "Hospitalizado",
    "verificado": false,
    "observacion": ""
  },
  {
    "nombre": "Dufiar Lopez",
    "cedula": "12115323",
    "edad": null,
    "sexo": "",
    "ubicacion": "Hospital Pérez Carreño",
    "origen": "",
    "estado": "Hospitalizado",
    "verificado": false,
    "observacion": "Revisar nombre"
  },
  {
    "nombre": "Meri Chavez",
    "cedula": "81462470",
    "edad": null,
    "sexo": "",
    "ubicacion": "Hospital Pérez Carreño",
    "origen": "",
    "estado": "Hospitalizado",
    "verificado": false,
    "observacion": ""
  },
  {
    "nombre": "Elisabeth Chacon",
    "cedula": "27374286",
    "edad": null,
    "sexo": "",
    "ubicacion": "Hospital Pérez Carreño",
    "origen": "",
    "estado": "Hospitalizado",
    "verificado": false,
    "observacion": ""
  },
  {
    "nombre": "Manuel Gomez",
    "cedula": "18814839",
    "edad": null,
    "sexo": "",
    "ubicacion": "Hospital Pérez Carreño",
    "origen": "",
    "estado": "Hospitalizado",
    "verificado": false,
    "observacion": ""
  },
  {
    "nombre": "Ibesen Iglesias",
    "cedula": "32357883",
    "edad": null,
    "sexo": "",
    "ubicacion": "Hospital Pérez Carreño",
    "origen": "",
    "estado": "Hospitalizado",
    "verificado": false,
    "observacion": "Revisar nombre"
  },
  {
    "nombre": "Fleci Valero",
    "cedula": "13574764",
    "edad": null,
    "sexo": "",
    "ubicacion": "Hospital Pérez Carreño",
    "origen": "",
    "estado": "Hospitalizado",
    "verificado": false,
    "observacion": "Revisar nombre"
  },
  {
    "nombre": "Javier Garcia",
    "cedula": "27377514",
    "edad": null,
    "sexo": "",
    "ubicacion": "Hospital Pérez Carreño",
    "origen": "",
    "estado": "Hospitalizado",
    "verificado": false,
    "observacion": ""
  },
  {
    "nombre": "Yordano Flores",
    "cedula": "",
    "edad": null,
    "sexo": "",
    "ubicacion": "Hospital Pérez Carreño",
    "origen": "Guaira",
    "estado": "Hospitalizado",
    "verificado": false,
    "observacion": ""
  },
  {
    "nombre": "Maria Pereira",
    "cedula": "",
    "edad": 8,
    "sexo": "",
    "ubicacion": "Hospital Dr. Ricardo Baquero",
    "origen": "",
    "estado": "Hospitalizado",
    "verificado": false,
    "observacion": ""
  },
  {
    "nombre": "Eduanvelis Cordoba",
    "cedula": "",
    "edad": 6,
    "sexo": "",
    "ubicacion": "Hospital Dr. Ricardo Baquero",
    "origen": "",
    "estado": "Hospitalizado",
    "verificado": false,
    "observacion": ""
  },
  {
    "nombre": "Yeison Tovar",
    "cedula": "",
    "edad": 16,
    "sexo": "",
    "ubicacion": "Hospital Dr. Ricardo Baquero",
    "origen": "",
    "estado": "Hospitalizado",
    "verificado": false,
    "observacion": ""
  },
  {
    "nombre": "Iesus Vegas",
    "cedula": "34273706",
    "edad": 14,
    "sexo": "",
    "ubicacion": "Hospital Dr. Ricardo Baquero",
    "origen": "",
    "estado": "Hospitalizado",
    "verificado": false,
    "observacion": "Revisar nombre/cédula"
  },
  {
    "nombre": "Daniela Carreño",
    "cedula": "32525559",
    "edad": 15,
    "sexo": "",
    "ubicacion": "Hospital Dr. Ricardo Baquero",
    "origen": "",
    "estado": "Hospitalizado",
    "verificado": false,
    "observacion": ""
  },
  {
    "nombre": "Iose Planas",
    "cedula": "12163470",
    "edad": 52,
    "sexo": "",
    "ubicacion": "Hospital Dr. Ricardo Baquero",
    "origen": "",
    "estado": "Hospitalizado",
    "verificado": false,
    "observacion": "Revisar nombre/cédula"
  },
  {
    "nombre": "Leoneidy Sivira",
    "cedula": "25175470",
    "edad": 30,
    "sexo": "",
    "ubicacion": "Hospital Dr. Ricardo Baquero",
    "origen": "",
    "estado": "Hospitalizado",
    "verificado": false,
    "observacion": ""
  },
  {
    "nombre": "Oscar Tortoso",
    "cedula": "6340991",
    "edad": 37,
    "sexo": "",
    "ubicacion": "Hospital Dr. Ricardo Baquero",
    "origen": "",
    "estado": "Hospitalizado",
    "verificado": false,
    "observacion": ""
  },
  {
    "nombre": "Kimberly Mora",
    "cedula": "24331288",
    "edad": 34,
    "sexo": "",
    "ubicacion": "Hospital Dr. Ricardo Baquero",
    "origen": "",
    "estado": "Hospitalizado",
    "verificado": false,
    "observacion": ""
  },
  {
    "nombre": "Reina Mendoza",
    "cedula": "6887465",
    "edad": 62,
    "sexo": "",
    "ubicacion": "Hospital Dr. Ricardo Baquero",
    "origen": "",
    "estado": "Hospitalizado",
    "verificado": false,
    "observacion": ""
  },
  {
    "nombre": "Iose Deagrela",
    "cedula": "13373135",
    "edad": 48,
    "sexo": "",
    "ubicacion": "Hospital Dr. Ricardo Baquero",
    "origen": "",
    "estado": "Hospitalizado",
    "verificado": false,
    "observacion": "Revisar nombre/cédula"
  },
  {
    "nombre": "Ingrid Lopez",
    "cedula": "10528878",
    "edad": 58,
    "sexo": "",
    "ubicacion": "Hospital Dr. Ricardo Baquero",
    "origen": "",
    "estado": "Hospitalizado",
    "verificado": false,
    "observacion": ""
  },
  {
    "nombre": "David Perez",
    "cedula": "6842773",
    "edad": 61,
    "sexo": "",
    "ubicacion": "Hospital Dr. Ricardo Baquero",
    "origen": "",
    "estado": "Hospitalizado",
    "verificado": false,
    "observacion": ""
  },
  {
    "nombre": "Amelis Alcantara",
    "cedula": "17443332",
    "edad": 39,
    "sexo": "",
    "ubicacion": "Hospital Dr. Ricardo Baquero",
    "origen": "",
    "estado": "Hospitalizado",
    "verificado": false,
    "observacion": ""
  },
  {
    "nombre": "Marco Gonzalez",
    "cedula": "10279036",
    "edad": 52,
    "sexo": "",
    "ubicacion": "Hospital Dr. Ricardo Baquero",
    "origen": "",
    "estado": "Hospitalizado",
    "verificado": false,
    "observacion": ""
  },
  {
    "nombre": "Iohn Iesel",
    "cedula": "3827925",
    "edad": 47,
    "sexo": "",
    "ubicacion": "Hospital Dr. Ricardo Baquero",
    "origen": "",
    "estado": "Hospitalizado",
    "verificado": false,
    "observacion": "Revisar nombre/cédula"
  },
  {
    "nombre": "Miriam Lopez",
    "cedula": "11",
    "edad": 38,
    "sexo": "",
    "ubicacion": "Hospital Dr. Ricardo Baquero",
    "origen": "",
    "estado": "Hospitalizado",
    "verificado": false,
    "observacion": "Revisar nombre/cédula"
  },
  {
    "nombre": "Miguel Rodrigue",
    "cedula": "100730429",
    "edad": 56,
    "sexo": "",
    "ubicacion": "Hospital Dr. Ricardo Baquero",
    "origen": "",
    "estado": "Hospitalizado",
    "verificado": false,
    "observacion": "Revisar nombre/cédula"
  },
  {
    "nombre": "Valella Georrin",
    "cedula": "30114918",
    "edad": 22,
    "sexo": "",
    "ubicacion": "Hospital Dr. Ricardo Baquero",
    "origen": "",
    "estado": "Hospitalizado",
    "verificado": false,
    "observacion": "Revisar nombre/cédula"
  },
  {
    "nombre": "Iohnson Estevez",
    "cedula": "29571733",
    "edad": 24,
    "sexo": "",
    "ubicacion": "Hospital Dr. Ricardo Baquero",
    "origen": "",
    "estado": "Hospitalizado",
    "verificado": false,
    "observacion": "Revisar nombre/cédula"
  },
  {
    "nombre": "Kelly Spinola",
    "cedula": "17482090",
    "edad": 38,
    "sexo": "",
    "ubicacion": "Hospital Dr. Ricardo Baquero",
    "origen": "",
    "estado": "Hospitalizado",
    "verificado": false,
    "observacion": ""
  },
  {
    "nombre": "Soilet Millan",
    "cedula": "18142695",
    "edad": 39,
    "sexo": "",
    "ubicacion": "Hospital Dr. Ricardo Baquero",
    "origen": "",
    "estado": "Hospitalizado",
    "verificado": false,
    "observacion": "Revisar nombre/cédula"
  },
  {
    "nombre": "Gustavo Mayora",
    "cedula": "11643841",
    "edad": 52,
    "sexo": "",
    "ubicacion": "Hospital Dr. Ricardo Baquero",
    "origen": "",
    "estado": "Hospitalizado",
    "verificado": false,
    "observacion": ""
  },
  {
    "nombre": "Ruben Jaímez",
    "cedula": "6433372",
    "edad": 74,
    "sexo": "",
    "ubicacion": "Hospital Dr. Ricardo Baquero",
    "origen": "",
    "estado": "Hospitalizado",
    "verificado": false,
    "observacion": ""
  },
  {
    "nombre": "Ana Abreu",
    "cedula": "22036301",
    "edad": 36,
    "sexo": "",
    "ubicacion": "Hospital Dr. Ricardo Baquero",
    "origen": "",
    "estado": "Hospitalizado",
    "verificado": false,
    "observacion": ""
  },
  {
    "nombre": "Silvia Yanes",
    "cedula": "3557870",
    "edad": 77,
    "sexo": "",
    "ubicacion": "Hospital Dr. Ricardo Baquero",
    "origen": "",
    "estado": "Hospitalizado",
    "verificado": false,
    "observacion": ""
  },
  {
    "nombre": "Abdelys Abdly",
    "cedula": "26254624",
    "edad": 28,
    "sexo": "",
    "ubicacion": "Hospital Dr. Ricardo Baquero",
    "origen": "",
    "estado": "Hospitalizado",
    "verificado": false,
    "observacion": ""
  },
  {
    "nombre": "Dilcia Lemus",
    "cedula": "13531664",
    "edad": 54,
    "sexo": "",
    "ubicacion": "Hospital Dr. Ricardo Baquero",
    "origen": "",
    "estado": "Hospitalizado",
    "verificado": false,
    "observacion": ""
  },
  {
    "nombre": "Margaret Pestano",
    "cedula": "19915985",
    "edad": 45,
    "sexo": "",
    "ubicacion": "Hospital Dr. Ricardo Baquero",
    "origen": "",
    "estado": "Hospitalizado",
    "verificado": false,
    "observacion": ""
  },
  {
    "nombre": "Alexandra Chirinos",
    "cedula": "31995517",
    "edad": 21,
    "sexo": "",
    "ubicacion": "Hospital Dr. Ricardo Baquero",
    "origen": "",
    "estado": "Hospitalizado",
    "verificado": false,
    "observacion": ""
  },
  {
    "nombre": "Irillia Semeria",
    "cedula": "",
    "edad": 49,
    "sexo": "",
    "ubicacion": "Hospital Dr. Ricardo Baquero",
    "origen": "",
    "estado": "Hospitalizado",
    "verificado": false,
    "observacion": "Revisar nombre/cédula"
  },
  {
    "nombre": "Yurmis Gonzalez",
    "cedula": "13828545",
    "edad": 47,
    "sexo": "",
    "ubicacion": "Hospital Dr. Ricardo Baquero",
    "origen": "",
    "estado": "Hospitalizado",
    "verificado": false,
    "observacion": ""
  },
  {
    "nombre": "Audia Teran",
    "cedula": "11055173",
    "edad": 54,
    "sexo": "",
    "ubicacion": "Hospital Dr. Ricardo Baquero",
    "origen": "",
    "estado": "Hospitalizado",
    "verificado": false,
    "observacion": ""
  },
  {
    "nombre": "Tenia Teran",
    "cedula": "11409997",
    "edad": 55,
    "sexo": "",
    "ubicacion": "Hospital Dr. Ricardo Baquero",
    "origen": "",
    "estado": "Hospitalizado",
    "verificado": false,
    "observacion": ""
  },
  {
    "nombre": "Valeria Lopez",
    "cedula": "31341560",
    "edad": 20,
    "sexo": "",
    "ubicacion": "Hospital Dr. Ricardo Baquero",
    "origen": "",
    "estado": "Hospitalizado",
    "verificado": false,
    "observacion": ""
  },
  {
    "nombre": "Yamileth Hernandez",
    "cedula": "",
    "edad": 61,
    "sexo": "",
    "ubicacion": "Hospital Dr. Ricardo Baquero",
    "origen": "",
    "estado": "Hospitalizado",
    "verificado": false,
    "observacion": ""
  },
  {
    "nombre": "Kimberly Mora",
    "cedula": "24334288",
    "edad": 34,
    "sexo": "",
    "ubicacion": "Hospital Dr. Ricardo Baquero",
    "origen": "",
    "estado": "Hospitalizado",
    "verificado": false,
    "observacion": ""
  },
  {
    "nombre": "Yolmar Cortez",
    "cedula": "6340999",
    "edad": 58,
    "sexo": "",
    "ubicacion": "Hospital Dr. Ricardo Baquero",
    "origen": "",
    "estado": "Hospitalizado",
    "verificado": false,
    "observacion": ""
  },
  {
    "nombre": "Yaneska Gonzalez",
    "cedula": "",
    "edad": 40,
    "sexo": "",
    "ubicacion": "Hospital Dr. Ricardo Baquero",
    "origen": "",
    "estado": "Hospitalizado",
    "verificado": false,
    "observacion": ""
  },
  {
    "nombre": "Anarella Machado",
    "cedula": "",
    "edad": 9,
    "sexo": "",
    "ubicacion": "Hospital Domingo Luciani",
    "origen": "",
    "estado": "Hospitalizado",
    "verificado": false,
    "observacion": ""
  },
  {
    "nombre": "Lewis Desmond",
    "cedula": "",
    "edad": 10,
    "sexo": "",
    "ubicacion": "Hospital Domingo Luciani",
    "origen": "",
    "estado": "Hospitalizado",
    "verificado": false,
    "observacion": ""
  },
  {
    "nombre": "Axiel Jimenez",
    "cedula": "",
    "edad": 4,
    "sexo": "",
    "ubicacion": "Hospital Domingo Luciani",
    "origen": "",
    "estado": "Hospitalizado",
    "verificado": false,
    "observacion": ""
  },
  {
    "nombre": "Carlos Chacon",
    "cedula": "",
    "edad": 13,
    "sexo": "",
    "ubicacion": "Hospital Domingo Luciani",
    "origen": "",
    "estado": "Hospitalizado",
    "verificado": false,
    "observacion": ""
  },
  {
    "nombre": "Gabriela Parra",
    "cedula": "",
    "edad": null,
    "sexo": "",
    "ubicacion": "Hospital Domingo Luciani",
    "origen": "",
    "estado": "Hospitalizado",
    "verificado": false,
    "observacion": ""
  },
  {
    "nombre": "Nancy Serrano",
    "cedula": "",
    "edad": null,
    "sexo": "",
    "ubicacion": "Hospital Domingo Luciani",
    "origen": "",
    "estado": "Hospitalizado",
    "verificado": false,
    "observacion": ""
  },
  {
    "nombre": "Doris Arrieta",
    "cedula": "",
    "edad": null,
    "sexo": "",
    "ubicacion": "Hospital Domingo Luciani",
    "origen": "",
    "estado": "Hospitalizado",
    "verificado": false,
    "observacion": ""
  },
  {
    "nombre": "Cirilo Jesus Pedron",
    "cedula": "",
    "edad": null,
    "sexo": "",
    "ubicacion": "Hospital Domingo Luciani",
    "origen": "",
    "estado": "Hospitalizado",
    "verificado": false,
    "observacion": ""
  },
  {
    "nombre": "Efren Guarini",
    "cedula": "",
    "edad": null,
    "sexo": "",
    "ubicacion": "Hospital Domingo Luciani",
    "origen": "",
    "estado": "Hospitalizado",
    "verificado": false,
    "observacion": ""
  },
  {
    "nombre": "Clara Lastra",
    "cedula": "",
    "edad": null,
    "sexo": "",
    "ubicacion": "Hospital Domingo Luciani",
    "origen": "",
    "estado": "Hospitalizado",
    "verificado": false,
    "observacion": ""
  },
  {
    "nombre": "Andreina Vasconcel",
    "cedula": "",
    "edad": null,
    "sexo": "",
    "ubicacion": "Hospital Domingo Luciani",
    "origen": "",
    "estado": "Hospitalizado",
    "verificado": false,
    "observacion": ""
  },
  {
    "nombre": "Rodosaui Padilla",
    "cedula": "",
    "edad": null,
    "sexo": "",
    "ubicacion": "Hospital Domingo Luciani",
    "origen": "",
    "estado": "Hospitalizado",
    "verificado": false,
    "observacion": "Revisar nombre"
  },
  {
    "nombre": "Omar Portillo",
    "cedula": "",
    "edad": null,
    "sexo": "",
    "ubicacion": "Hospital Domingo Luciani",
    "origen": "",
    "estado": "Hospitalizado",
    "verificado": false,
    "observacion": ""
  },
  {
    "nombre": "Luisana Ordaz",
    "cedula": "",
    "edad": null,
    "sexo": "",
    "ubicacion": "Hospital Domingo Luciani",
    "origen": "",
    "estado": "Hospitalizado",
    "verificado": false,
    "observacion": ""
  },
  {
    "nombre": "Eduardo Rodrigue",
    "cedula": "",
    "edad": null,
    "sexo": "",
    "ubicacion": "Hospital Domingo Luciani",
    "origen": "",
    "estado": "Hospitalizado",
    "verificado": false,
    "observacion": ""
  },
  {
    "nombre": "Sofia Blanco",
    "cedula": "",
    "edad": null,
    "sexo": "",
    "ubicacion": "Hospital Domingo Luciani",
    "origen": "",
    "estado": "Hospitalizado",
    "verificado": false,
    "observacion": ""
  },
  {
    "nombre": "Rene Suarez",
    "cedula": "",
    "edad": null,
    "sexo": "",
    "ubicacion": "Hospital Domingo Luciani",
    "origen": "",
    "estado": "Hospitalizado",
    "verificado": false,
    "observacion": ""
  },
  {
    "nombre": "Carmen Blanco",
    "cedula": "",
    "edad": null,
    "sexo": "",
    "ubicacion": "Hospital Domingo Luciani",
    "origen": "",
    "estado": "Hospitalizado",
    "verificado": false,
    "observacion": ""
  },
  {
    "nombre": "Alberto Fuentes",
    "cedula": "",
    "edad": null,
    "sexo": "",
    "ubicacion": "Hospital Domingo Luciani",
    "origen": "",
    "estado": "Hospitalizado",
    "verificado": false,
    "observacion": "Revisar nombre"
  },
  {
    "nombre": "Yosiany Garavito",
    "cedula": "",
    "edad": null,
    "sexo": "",
    "ubicacion": "Hospital Domingo Luciani",
    "origen": "",
    "estado": "Hospitalizado",
    "verificado": false,
    "observacion": ""
  },
  {
    "nombre": "Mariangel Ramirez",
    "cedula": "",
    "edad": null,
    "sexo": "",
    "ubicacion": "Hospital Domingo Luciani",
    "origen": "",
    "estado": "Hospitalizado",
    "verificado": false,
    "observacion": ""
  },
  {
    "nombre": "Gladiuska Herrera",
    "cedula": "",
    "edad": null,
    "sexo": "",
    "ubicacion": "Hospital Domingo Luciani",
    "origen": "",
    "estado": "Hospitalizado",
    "verificado": false,
    "observacion": ""
  },
  {
    "nombre": "Frarnir Rivas",
    "cedula": "",
    "edad": null,
    "sexo": "",
    "ubicacion": "Hospital Domingo Luciani",
    "origen": "",
    "estado": "Hospitalizado",
    "verificado": false,
    "observacion": "Revisar nombre"
  },
  {
    "nombre": "Yessica Blanco",
    "cedula": "",
    "edad": null,
    "sexo": "",
    "ubicacion": "Hospital Domingo Luciani",
    "origen": "",
    "estado": "Hospitalizado",
    "verificado": false,
    "observacion": ""
  },
  {
    "nombre": "Diego Obregon",
    "cedula": "",
    "edad": null,
    "sexo": "",
    "ubicacion": "Hospital Domingo Luciani",
    "origen": "",
    "estado": "Hospitalizado",
    "verificado": false,
    "observacion": ""
  },
  {
    "nombre": "Alexandra Gonzalez",
    "cedula": "",
    "edad": null,
    "sexo": "",
    "ubicacion": "Hospital Domingo Luciani",
    "origen": "",
    "estado": "Hospitalizado",
    "verificado": false,
    "observacion": ""
  },
  {
    "nombre": "Corina Cabrera",
    "cedula": "",
    "edad": null,
    "sexo": "",
    "ubicacion": "Hospital Domingo Luciani",
    "origen": "",
    "estado": "Hospitalizado",
    "verificado": false,
    "observacion": ""
  },
  {
    "nombre": "Aide Arteaga",
    "cedula": "",
    "edad": null,
    "sexo": "",
    "ubicacion": "Hospital Domingo Luciani",
    "origen": "",
    "estado": "Hospitalizado",
    "verificado": false,
    "observacion": ""
  },
  {
    "nombre": "Brayan Vilchez",
    "cedula": "",
    "edad": 23,
    "sexo": "",
    "ubicacion": "Hospital Domingo Luciani",
    "origen": "",
    "estado": "Hospitalizado",
    "verificado": false,
    "observacion": ""
  },
  {
    "nombre": "Alberto Fuente",
    "cedula": "",
    "edad": 22,
    "sexo": "",
    "ubicacion": "Hospital Domingo Luciani",
    "origen": "",
    "estado": "Hospitalizado",
    "verificado": false,
    "observacion": "Revisar nombre"
  },
  {
    "nombre": "Francisca Perez",
    "cedula": "",
    "edad": 63,
    "sexo": "",
    "ubicacion": "Hospital Domingo Luciani",
    "origen": "",
    "estado": "Hospitalizado",
    "verificado": false,
    "observacion": ""
  },
  {
    "nombre": "Ioseani Marabito",
    "cedula": "",
    "edad": 32,
    "sexo": "",
    "ubicacion": "Hospital Domingo Luciani",
    "origen": "",
    "estado": "Hospitalizado",
    "verificado": false,
    "observacion": "Revisar nombre"
  },
  {
    "nombre": "Matilde Abello",
    "cedula": "",
    "edad": 36,
    "sexo": "",
    "ubicacion": "Hospital Domingo Luciani",
    "origen": "",
    "estado": "Hospitalizado",
    "verificado": false,
    "observacion": ""
  },
  {
    "nombre": "Eduardo Rodrigue",
    "cedula": "",
    "edad": 65,
    "sexo": "",
    "ubicacion": "Hospital Domingo Luciani",
    "origen": "",
    "estado": "Hospitalizado",
    "verificado": false,
    "observacion": ""
  },
  {
    "nombre": "Divito Rosa",
    "cedula": "",
    "edad": 64,
    "sexo": "",
    "ubicacion": "Hospital Domingo Luciani",
    "origen": "",
    "estado": "Hospitalizado",
    "verificado": false,
    "observacion": ""
  },
  {
    "nombre": "Deiverson Guerrero",
    "cedula": "",
    "edad": 20,
    "sexo": "",
    "ubicacion": "Hospital Domingo Luciani",
    "origen": "",
    "estado": "Hospitalizado",
    "verificado": false,
    "observacion": ""
  },
  {
    "nombre": "Armando Cordova",
    "cedula": "",
    "edad": 19,
    "sexo": "",
    "ubicacion": "Hospital Domingo Luciani",
    "origen": "",
    "estado": "Hospitalizado",
    "verificado": false,
    "observacion": ""
  },
  {
    "nombre": "Iennicel Rey",
    "cedula": "",
    "edad": 29,
    "sexo": "",
    "ubicacion": "Hospital Domingo Luciani",
    "origen": "",
    "estado": "Hospitalizado",
    "verificado": false,
    "observacion": "Revisar nombre"
  },
  {
    "nombre": "Daniel Rivero",
    "cedula": "",
    "edad": 60,
    "sexo": "",
    "ubicacion": "Hospital Domingo Luciani",
    "origen": "",
    "estado": "Hospitalizado",
    "verificado": false,
    "observacion": ""
  },
  {
    "nombre": "Iose Blanco",
    "cedula": "",
    "edad": 6,
    "sexo": "",
    "ubicacion": "Hospital Domingo Luciani",
    "origen": "",
    "estado": "Hospitalizado",
    "verificado": false,
    "observacion": "Revisar nombre"
  },
  {
    "nombre": "Neisy Fernande",
    "cedula": "",
    "edad": 37,
    "sexo": "",
    "ubicacion": "Hospital Domingo Luciani",
    "origen": "",
    "estado": "Hospitalizado",
    "verificado": false,
    "observacion": ""
  },
  {
    "nombre": "Isael Acosta",
    "cedula": "",
    "edad": 10,
    "sexo": "",
    "ubicacion": "Hospital Domingo Luciani",
    "origen": "",
    "estado": "Hospitalizado",
    "verificado": false,
    "observacion": ""
  },
  {
    "nombre": "Alexander Acosta",
    "cedula": "",
    "edad": 47,
    "sexo": "",
    "ubicacion": "Hospital Domingo Luciani",
    "origen": "",
    "estado": "Hospitalizado",
    "verificado": false,
    "observacion": ""
  },
  {
    "nombre": "Hasael Acosta",
    "cedula": "",
    "edad": 13,
    "sexo": "",
    "ubicacion": "Hospital Domingo Luciani",
    "origen": "",
    "estado": "Hospitalizado",
    "verificado": false,
    "observacion": ""
  },
  {
    "nombre": "Maria Betancou",
    "cedula": "",
    "edad": 74,
    "sexo": "",
    "ubicacion": "Hospital Domingo Luciani",
    "origen": "",
    "estado": "Hospitalizado",
    "verificado": false,
    "observacion": ""
  },
  {
    "nombre": "Iraima Izquierdo",
    "cedula": "",
    "edad": 83,
    "sexo": "",
    "ubicacion": "Hospital Domingo Luciani",
    "origen": "",
    "estado": "Hospitalizado",
    "verificado": false,
    "observacion": ""
  },
  {
    "nombre": "Luis Vazquez",
    "cedula": "",
    "edad": 77,
    "sexo": "",
    "ubicacion": "Hospital Domingo Luciani",
    "origen": "",
    "estado": "Hospitalizado",
    "verificado": false,
    "observacion": ""
  },
  {
    "nombre": "Manuel Albe",
    "cedula": "",
    "edad": 77,
    "sexo": "",
    "ubicacion": "Hospital Domingo Luciani",
    "origen": "",
    "estado": "Hospitalizado",
    "verificado": false,
    "observacion": ""
  },
  {
    "nombre": "Albimar Gonzalez",
    "cedula": "",
    "edad": 59,
    "sexo": "",
    "ubicacion": "Hospital Domingo Luciani",
    "origen": "",
    "estado": "Hospitalizado",
    "verificado": false,
    "observacion": ""
  },
  {
    "nombre": "Efrain Fernande",
    "cedula": "",
    "edad": 31,
    "sexo": "",
    "ubicacion": "Hospital Domingo Luciani",
    "origen": "",
    "estado": "Hospitalizado",
    "verificado": false,
    "observacion": ""
  },
  {
    "nombre": "Yesire Mendez",
    "cedula": "",
    "edad": 24,
    "sexo": "",
    "ubicacion": "Hospital Domingo Luciani",
    "origen": "",
    "estado": "Hospitalizado",
    "verificado": false,
    "observacion": ""
  },
  {
    "nombre": "Estefania Parra",
    "cedula": "",
    "edad": 15,
    "sexo": "",
    "ubicacion": "Hospital Domingo Luciani",
    "origen": "",
    "estado": "Hospitalizado",
    "verificado": false,
    "observacion": ""
  },
  {
    "nombre": "Edimar Delgado",
    "cedula": "",
    "edad": 23,
    "sexo": "",
    "ubicacion": "Hospital Domingo Luciani",
    "origen": "",
    "estado": "Hospitalizado",
    "verificado": false,
    "observacion": ""
  },
  {
    "nombre": "Ana Ibarra",
    "cedula": "",
    "edad": 74,
    "sexo": "",
    "ubicacion": "Hospital Domingo Luciani",
    "origen": "",
    "estado": "Hospitalizado",
    "verificado": false,
    "observacion": ""
  },
  {
    "nombre": "Nuvia Torrealba",
    "cedula": "",
    "edad": 68,
    "sexo": "",
    "ubicacion": "Hospital Domingo Luciani",
    "origen": "",
    "estado": "Hospitalizado",
    "verificado": false,
    "observacion": ""
  },
  {
    "nombre": "Yenny Garcia",
    "cedula": "",
    "edad": 34,
    "sexo": "",
    "ubicacion": "Hospital Domingo Luciani",
    "origen": "",
    "estado": "Hospitalizado",
    "verificado": false,
    "observacion": "Revisar nombre"
  },
  {
    "nombre": "Yenny Iscala",
    "cedula": "",
    "edad": 42,
    "sexo": "",
    "ubicacion": "Hospital Domingo Luciani",
    "origen": "",
    "estado": "Hospitalizado",
    "verificado": false,
    "observacion": "Revisar nombre"
  },
  {
    "nombre": "Paulina Abreu",
    "cedula": "",
    "edad": 8,
    "sexo": "",
    "ubicacion": "Hospital Domingo Luciani",
    "origen": "",
    "estado": "Hospitalizado",
    "verificado": false,
    "observacion": ""
  },
  {
    "nombre": "Rafael Rojas",
    "cedula": "",
    "edad": 50,
    "sexo": "",
    "ubicacion": "Hospital Domingo Luciani",
    "origen": "",
    "estado": "Hospitalizado",
    "verificado": false,
    "observacion": ""
  },
  {
    "nombre": "Stephany Gonzalez",
    "cedula": "",
    "edad": 22,
    "sexo": "",
    "ubicacion": "Hospital Domingo Luciani",
    "origen": "",
    "estado": "Hospitalizado",
    "verificado": false,
    "observacion": ""
  },
  {
    "nombre": "Rafael Gonzalez",
    "cedula": "",
    "edad": 39,
    "sexo": "",
    "ubicacion": "Hospital Domingo Luciani",
    "origen": "",
    "estado": "Hospitalizado",
    "verificado": false,
    "observacion": ""
  },
  {
    "nombre": "Iuan Castro",
    "cedula": "",
    "edad": 26,
    "sexo": "",
    "ubicacion": "Hospital Domingo Luciani",
    "origen": "",
    "estado": "Hospitalizado",
    "verificado": false,
    "observacion": "Revisar nombre"
  },
  {
    "nombre": "Ivis Escalona",
    "cedula": "",
    "edad": 55,
    "sexo": "",
    "ubicacion": "Hospital Domingo Luciani",
    "origen": "",
    "estado": "Hospitalizado",
    "verificado": false,
    "observacion": "Revisar nombre"
  },
  {
    "nombre": "Iosefina Muñoz",
    "cedula": "",
    "edad": 72,
    "sexo": "",
    "ubicacion": "Hospital Domingo Luciani",
    "origen": "",
    "estado": "Hospitalizado",
    "verificado": false,
    "observacion": "Revisar nombre"
  },
  {
    "nombre": "Luisana Ordaz",
    "cedula": "",
    "edad": 58,
    "sexo": "",
    "ubicacion": "Hospital Domingo Luciani",
    "origen": "",
    "estado": "Hospitalizado",
    "verificado": false,
    "observacion": ""
  },
  {
    "nombre": "Miel Frontrad",
    "cedula": "",
    "edad": 7,
    "sexo": "",
    "ubicacion": "Hospital Domingo Luciani",
    "origen": "",
    "estado": "Hospitalizado",
    "verificado": false,
    "observacion": "Revisar nombre"
  },
  {
    "nombre": "Rafael Goyo",
    "cedula": "",
    "edad": 32,
    "sexo": "",
    "ubicacion": "Hospital Domingo Luciani",
    "origen": "",
    "estado": "Hospitalizado",
    "verificado": false,
    "observacion": ""
  },
  {
    "nombre": "Frankelin Rivas",
    "cedula": "",
    "edad": 53,
    "sexo": "",
    "ubicacion": "Hospital Domingo Luciani",
    "origen": "",
    "estado": "Hospitalizado",
    "verificado": false,
    "observacion": ""
  },
  {
    "nombre": "Elian Trujillo",
    "cedula": "",
    "edad": 19,
    "sexo": "",
    "ubicacion": "Hospital Domingo Luciani",
    "origen": "",
    "estado": "Hospitalizado",
    "verificado": false,
    "observacion": ""
  },
  {
    "nombre": "Katiuska Marcano",
    "cedula": "",
    "edad": 56,
    "sexo": "",
    "ubicacion": "Hospital Domingo Luciani",
    "origen": "",
    "estado": "Hospitalizado",
    "verificado": false,
    "observacion": ""
  },
  {
    "nombre": "Kellys Winchest",
    "cedula": "",
    "edad": 28,
    "sexo": "",
    "ubicacion": "Hospital Domingo Luciani",
    "origen": "",
    "estado": "Hospitalizado",
    "verificado": false,
    "observacion": ""
  },
  {
    "nombre": "Samuel Vega",
    "cedula": "",
    "edad": 11,
    "sexo": "",
    "ubicacion": "Hospital Domingo Luciani",
    "origen": "",
    "estado": "Hospitalizado",
    "verificado": false,
    "observacion": ""
  },
  {
    "nombre": "Angel Rondon",
    "cedula": "",
    "edad": 12,
    "sexo": "",
    "ubicacion": "Hospital Domingo Luciani",
    "origen": "",
    "estado": "Hospitalizado",
    "verificado": false,
    "observacion": ""
  },
  {
    "nombre": "Guillermina Rengifo",
    "cedula": "",
    "edad": 46,
    "sexo": "",
    "ubicacion": "Hospital Domingo Luciani",
    "origen": "",
    "estado": "Hospitalizado",
    "verificado": false,
    "observacion": ""
  },
  {
    "nombre": "Olga Gonzalez",
    "cedula": "",
    "edad": 63,
    "sexo": "",
    "ubicacion": "Hospital Domingo Luciani",
    "origen": "",
    "estado": "Hospitalizado",
    "verificado": false,
    "observacion": ""
  },
  {
    "nombre": "Isolibeth Mijeras",
    "cedula": "",
    "edad": 45,
    "sexo": "",
    "ubicacion": "Hospital Domingo Luciani",
    "origen": "",
    "estado": "Hospitalizado",
    "verificado": false,
    "observacion": "Revisar nombre"
  },
  {
    "nombre": "Silibeto Urbina",
    "cedula": "",
    "edad": 80,
    "sexo": "",
    "ubicacion": "Hospital Domingo Luciani",
    "origen": "",
    "estado": "Hospitalizado",
    "verificado": false,
    "observacion": "Revisar nombre"
  },
  {
    "nombre": "Liliani Bolges",
    "cedula": "",
    "edad": 21,
    "sexo": "",
    "ubicacion": "Hospital Domingo Luciani",
    "origen": "",
    "estado": "Hospitalizado",
    "verificado": false,
    "observacion": "Revisar nombre"
  },
  {
    "nombre": "Suhyn Alayon",
    "cedula": "",
    "edad": 25,
    "sexo": "",
    "ubicacion": "Hospital Domingo Luciani",
    "origen": "",
    "estado": "Hospitalizado",
    "verificado": false,
    "observacion": "Revisar nombre"
  },
  {
    "nombre": "Haddy Lopez",
    "cedula": "",
    "edad": 42,
    "sexo": "",
    "ubicacion": "Hospital Domingo Luciani",
    "origen": "",
    "estado": "Hospitalizado",
    "verificado": false,
    "observacion": "Revisar nombre"
  },
  {
    "nombre": "Milagros Torres",
    "cedula": "",
    "edad": 46,
    "sexo": "",
    "ubicacion": "Hospital Domingo Luciani",
    "origen": "",
    "estado": "Hospitalizado",
    "verificado": false,
    "observacion": ""
  },
  {
    "nombre": "Gladys Arteaga",
    "cedula": "",
    "edad": 72,
    "sexo": "",
    "ubicacion": "Hospital Domingo Luciani",
    "origen": "",
    "estado": "Hospitalizado",
    "verificado": false,
    "observacion": ""
  }
]